aws_replicator/__init__.py
aws_replicator/config.py
aws_replicator/client/__init__.py
aws_replicator/client/auth_proxy.py
aws_replicator/client/cli.py
aws_replicator/client/http2_server.py
aws_replicator/client/replicate.py
aws_replicator/client/service_states.py
aws_replicator/client/utils.py
aws_replicator/server/__init__.py
aws_replicator/server/aws_request_forwarder.py
aws_replicator/server/extension.py
aws_replicator/server/request_handler.py
aws_replicator/server/resource_replicator.py
aws_replicator/server/ui/__init__.py
aws_replicator/server/ui/app.js
aws_replicator/server/ui/favicon.png
aws_replicator/server/ui/index.html
aws_replicator/shared/__init__.py
aws_replicator/shared/constants.py
aws_replicator/shared/models.py
aws_replicator/shared/utils.py
tests/__init__.py
tests/conftest.py
tests/test_config.py
tests/test_proxy_requests.py
localstack_extension_aws_replicator-0.1.25.dist-info/METADATA
localstack_extension_aws_replicator-0.1.25.dist-info/WHEEL
localstack_extension_aws_replicator-0.1.25.dist-info/entry_points.txt
localstack_extension_aws_replicator-0.1.25.dist-info/top_level.txt
localstack_extension_aws_replicator-0.1.25.dist-info/RECORD
